<?xml version="1.0" encoding="UTF-8"?>
<mods xmlns:xsi="http://www.w3.org/2001/XMLSchema-instance"
      version="3.7"
      xsi:schemaLocation="http://www.loc.gov/mods/v3 http://www.loc.gov/standards/mods/v3/mods-3-7.xsd">
   <titleInfo>
      <title>Assessment of respiratory function in children wearing a N95 mask with or without an exhalation valve: Data compared</title>
   </titleInfo>
   <name type="personal" usage="primary">
      <namePart type="given">Riccardo</namePart>
      <namePart type="family">Lubrano</namePart>
      <nameIdentifier type="orcid">https://orcid.org/0000-0001-8237-955X</nameIdentifier>
      <displayForm>Lubrano, Riccardo</displayForm>
      <affiliation>Dipartimento Materno Infantile e di Scienze Urologiche, Sapienza Università di Roma, UOC di Pediatria e Neonatologia - Polo Pontino, Italy</affiliation>
      <role>
         <roleTerm type="text">author</roleTerm>
      </role>
   </name>
   <name type="personal">
      <namePart type="given">Silvia</namePart>
      <namePart type="family">Bloise</namePart>
      <displayForm>Bloise, Silvia</displayForm>
      <role>
         <roleTerm type="text">author</roleTerm>
      </role>
   </name>
   <name type="personal">
      <namePart type="given">Alessia</namePart>
      <namePart type="family">Marcellino</namePart>
      <displayForm>Marcellino, Alessia</displayForm>
      <affiliation>Dipartimento Materno Infantile e di Scienze Urologiche, Sapienza Università di Roma, UOC di Pediatria e Neonatologia - Polo Pontino, Italy</affiliation>
      <role>
         <roleTerm type="text">author</roleTerm>
      </role>
   </name>
   <name type="personal">
      <namePart type="given">Claudia</namePart>
      <namePart type="family">Proietti Ciolli</namePart>
      <displayForm>Proietti Ciolli, Claudia</displayForm>
      <affiliation>Dipartimento Materno Infantile e di Scienze Urologiche, Sapienza Università di Roma, UOC di Pediatria e Neonatologia - Polo Pontino, Italy</affiliation>
      <role>
         <roleTerm type="text">author</roleTerm>
      </role>
   </name>
   <name type="personal">
      <namePart type="given">Alessia</namePart>
      <namePart type="family">Testa</namePart>
      <displayForm>Testa, Alessia</displayForm>
      <affiliation>Dipartimento Materno Infantile e di Scienze Urologiche, Sapienza Università di Roma, UOC di Pediatria e Neonatologia - Polo Pontino, Italy</affiliation>
      <role>
         <roleTerm type="text">author</roleTerm>
      </role>
   </name>
   <name type="personal">
      <namePart type="given">Enrica</namePart>
      <namePart type="family">De Luca</namePart>
      <displayForm>De Luca, Enrica</displayForm>
      <affiliation>Dipartimento Materno Infantile e di Scienze Urologiche, Sapienza Università di Roma, UOC di Pediatria e Neonatologia - Polo Pontino, Italy</affiliation>
      <role>
         <roleTerm type="text">author</roleTerm>
      </role>
   </name>
   <name type="personal">
      <namePart type="given">Anna</namePart>
      <namePart type="family">Dilillo</namePart>
      <displayForm>Dilillo, Anna</displayForm>
      <affiliation>Dipartimento Materno Infantile e di Scienze Urologiche, Sapienza Università di Roma, UOC di Pediatria e Neonatologia - Polo Pontino, Italy</affiliation>
      <role>
         <roleTerm type="text">author</roleTerm>
      </role>
   </name>
   <name type="personal">
      <namePart type="given">Saverio</namePart>
      <namePart type="family">Mallardo</namePart>
      <nameIdentifier type="orcid">https://orcid.org/0000-0001-7412-2279</nameIdentifier>
      <displayForm>Mallardo, Saverio</displayForm>
      <affiliation>Dipartimento Materno Infantile e di Scienze Urologiche, Sapienza Università di Roma, UOC di Pediatria e Neonatologia - Polo Pontino, Italy</affiliation>
      <role>
         <roleTerm type="text">author</roleTerm>
      </role>
   </name>
   <name type="personal">
      <namePart type="given">Sara</namePart>
      <namePart type="family">Isoldi</namePart>
      <nameIdentifier type="orcid">https://orcid.org/0000-0001-8390-5371</nameIdentifier>
      <displayForm>Isoldi, Sara</displayForm>
      <affiliation>Dipartimento Materno Infantile e di Scienze Urologiche, Sapienza Università di Roma, UOC di Pediatria e Neonatologia - Polo Pontino, Italy</affiliation>
      <role>
         <roleTerm type="text">author</roleTerm>
      </role>
   </name>
   <name type="personal">
      <namePart type="given">Vanessa</namePart>
      <namePart type="family">Martucci</namePart>
      <displayForm>Martucci, Vanessa</displayForm>
      <affiliation>Dipartimento Materno Infantile e di Scienze Urologiche, Sapienza Università di Roma, UOC di Pediatria e Neonatologia - Polo Pontino, Italy</affiliation>
      <role>
         <roleTerm type="text">author</roleTerm>
      </role>
   </name>
   <name type="personal">
      <namePart type="given">Mariateresa</namePart>
      <namePart type="family">Sanseviero</namePart>
      <nameIdentifier type="orcid">https://orcid.org/0000-0001-7935-6648</nameIdentifier>
      <displayForm>Sanseviero, Mariateresa</displayForm>
      <affiliation>Dipartimento Materno Infantile e di Scienze Urologiche, Sapienza Università di Roma, UOC di Pediatria e Neonatologia - Polo Pontino, Italy</affiliation>
      <role>
         <roleTerm type="text">author</roleTerm>
      </role>
   </name>
   <name type="personal">
      <namePart type="given">Emanuela</namePart>
      <namePart type="family">Del Giudice</namePart>
      <nameIdentifier type="orcid">https://orcid.org/0000-0002-3334-4884</nameIdentifier>
      <displayForm>Del Giudice, Emanuela</displayForm>
      <affiliation>Dipartimento Materno Infantile e di Scienze Urologiche, Sapienza Università di Roma, UOC di Pediatria e Neonatologia - Polo Pontino, Italy</affiliation>
      <role>
         <roleTerm type="text">author</roleTerm>
      </role>
   </name>
   <name type="personal">
      <namePart type="given">Concetta</namePart>
      <namePart type="family">Malvaso</namePart>
      <displayForm>Malvaso, Concetta</displayForm>
      <affiliation>Dipartimento Materno Infantile e di Scienze Urologiche, Sapienza Università di Roma, UOC di Pediatria e Neonatologia - Polo Pontino, Italy</affiliation>
      <role>
         <roleTerm type="text">author</roleTerm>
      </role>
   </name>
   <name type="personal">
      <namePart type="given">Claudio</namePart>
      <namePart type="family">Iacovelli</namePart>
      <displayForm>Iacovelli, Claudio</displayForm>
      <affiliation>Dipartimento Materno Infantile e di Scienze Urologiche, Sapienza Università di Roma, UOC di Pediatria e Neonatologia - Polo Pontino, Italy</affiliation>
      <role>
         <roleTerm type="text">author</roleTerm>
      </role>
   </name>
   <name type="personal">
      <namePart type="given">Rita</namePart>
      <namePart type="family">Leone</namePart>
      <displayForm>Leone, Rita</displayForm>
      <affiliation>Dipartimento Materno Infantile e di Scienze Urologiche, Sapienza Università di Roma, UOC di Pediatria e Neonatologia - Polo Pontino, Italy</affiliation>
      <role>
         <roleTerm type="text">author</roleTerm>
      </role>
   </name>
   <name type="personal">
      <namePart type="given">Donatella</namePart>
      <namePart type="family">Iorfida</namePart>
      <nameIdentifier type="orcid">https://orcid.org/0000-0002-5288-6371</nameIdentifier>
      <displayForm>Iorfida, Donatella</displayForm>
      <affiliation>Dipartimento Materno Infantile e di Scienze Urologiche, Sapienza Università di Roma, UOC di Pediatria e Neonatologia - Polo Pontino, Italy</affiliation>
      <role>
         <roleTerm type="text">author</roleTerm>
      </role>
   </name>
   <name type="personal">
      <namePart type="given">Flavia</namePart>
      <namePart type="family">Ventriglia</namePart>
      <displayForm>Ventriglia, Flavia</displayForm>
      <affiliation>Dipartimento Materno Infantile e di Scienze Urologiche, Sapienza Università di Roma, UOC di Pediatria e Neonatologia - Polo Pontino, Italy</affiliation>
      <role>
         <roleTerm type="text">author</roleTerm>
      </role>
   </name>
   <typeOfResource>text</typeOfResource>
   <genre>article</genre>
   <originInfo>
      <dateIssued encoding="w3cdtf" keyDate="yes">2021-12</dateIssued>
   </originInfo>
   <language>
      <languageTerm type="code" authority="iso639-2b">eng</languageTerm>
      <languageTerm type="text">English</languageTerm>
   </language>
   <abstract>In response to the current COVID-19 pandemic, universal face masking represents one of the most important strategies to limit the spread of infection. However, their use in children is still highly debated (Esposito and Principi, 2020; Esposito et al., 2020) and there are few data (Lubrano et al., 2021a, 2021b) describing their possible effects on respiratory function in children. A dataset in this paper presents a comparison of the data related to the effects on respiratory function of children wearing a filtering facepiece 2 (N95 mask) with or without exhalation valve. 22 healthy children were randomly assigned to two groups, both groups wearing an N95 mask: one without an exhalation valve (group A), another with an exhalation valve (group B). Children were subjected to a 72 min test: the first 30 min without mask, then 30 min wearing face mask while practiced their usual play activity; finally, 12 min, with face mask in place, while they walked as in a walking test. They were monitored through to microstream capnography system (Rad-97TM with Nomo-Line Capnography, Masimo, Irvine, CA, USA) to log oxygen saturation (SpO2) and respiratory rate (RR). We use the Wilcoxon test to analyzed the differences between the parameters recorded during the study in group A and B. Data analysis was performed using JMP14.3.0 program for Mac by SAS Institute inc. </abstract>
   <subject>
      <topic>COVID-19</topic>
   </subject>
   <subject>
      <topic>Facial mask</topic>
   </subject>
   <subject>
      <topic>Respiratory function</topic>
   </subject>
   <subject>
      <topic>Children</topic>
   </subject>
   <relatedItem type="host">
      <titleInfo>
         <title>Data in Brief</title>
      </titleInfo>
      <originInfo>
         <publisher>Elsevier Inc.</publisher>
      </originInfo>
      <identifier type="issn">2352-3409</identifier>
      <part>
         <detail type="volume">
            <number>39</number>
            <caption>v.</caption>
         </detail>
         <text type="display-date">December 2021</text>
         <text type="year">2021</text>
         <text type="month">December</text>
         <extent unit="pages">
            <start>107550</start>
         </extent>
      </part>
   </relatedItem>
   <identifier type="doi">10.1016/j.dib.2021.107550</identifier>
   <location>
      <url>http://dx.doi.org/10.1016/j.dib.2021.107550</url>
   </location>
   <identifier type="pii">S2352-3409(21)00826-X</identifier>
   <accessCondition type="use and reproduction"
                    displayLabel="Creative Commons Attribution 4.0 Generic (CC BY 4.0)">
      <program xmlns="https://data.crossref.org/schemas/AccessIndicators.xsd">
         <licence_ref applies_to="reuse" start_date="2021-11-02"/>
         <licence_ref>http://creativecommons.org/licenses/by/4.0/</licence_ref>
      </program>
   </accessCondition>
   <extension>
      <vendorName/>
      <archiveFile/>
      <originalFile>file:/C:/Users/Carlos.Martinez/OneDrive%20-%20USDA/XML_projects/OpenAccess/OpenAccess/transform/source/sourcefiles/164128545923847224-00001/2352-3409/S2352340921X00066/S235234092100826X/S235234092100826X.xml</originalFile>
      <workingDirectory>C:\Users\Carlos.Martinez\OneDrive - USDA\XML_projects\OpenAccess\OpenAccess\transform\result\</workingDirectory>
   </extension>
</mods>
